[
  {
    "id": 1,
    "nome": "Animais Universitários",
    "subtitulo": "Projeto voluntário de assistência aos animais abandonados no Campus do Pici",
    "localizacao": " Fortaleza - CE, UFC - Campus do Pici",
    "descricao": "Projeto voluntário que atua no Campus do Pici (UFC), promovendo castrações, adoções e cuidados básicos a animais abandonados. A iniciativa é mantida por doações e bazares, sem apoio institucional, e depende de lares temporários para acolher os animais.",
    "tags": ["Instagram", "Email", "Linktree"],
    "logo": "/ongslogos/animaisuniversitarioslogo.png",
    "links": {
      "instagram": "https://www.instagram.com/animaisuniversitarios",
      "email" : "projetoanimaisuniversitarios@gmail.com",
      "linktree": "linktr.ee/animaisuniversitarios"
    },
    "contatos": {
      "email": "contato@gatinhosfortaleza.org",
      "telefone": "(85) 98907-9977"
    },
    "doacoes": {
      "pix": "XX.345.678/0001-XX",
      "banco": "Banco do Brasil - Ag: 1234-X C/C: 12345-6"
    }
  },
  {
    "id": 2,
    "nome": "Adote um Bigode",
    "subtitulo": "Alimentamos +100 animais, castramos e promovemos adoção dos que cruzam nosso caminho",
    "localizacao": "Fortaleza, CE",
    "descricao": "Alimentamos diariamente mais de 100 animais. São dois pontos de abandono na cidade de Fortaleza. São 90 kg de ração por semana. Além disso resgatamos os mais debilitados e reabilitamos para irem para adoção.  Também realizamos a castração dos animais para evitar a superpopulação.  ",
    "tags": ["Instagram", "Email", "Linktree"],
    "logo": "/ongslogos/adoteumbigodelogo.png",
    "links": {
      "instagram": "https://www.instagram.com/adoteumbigodeceara",
      "email" : "Adoteumbigodece@gmail.com",
      "linktree": "linktr.ee/adoteumbigodece"
    },
    "contatos": {
      "email": "adoteumbigodece@gmail.com",
      "telefone": "(85) 3333-3333"
    },
    "doacoes": {
      "pix": "@email.com",
      "banco": "Caixa Econômica - Ag: 0001 C/C: 1234-X"
    }
  },
  {
    "id": 3,
    "nome": "ONG Abrace",
    "subtitulo": "ABRACE - Uma causa animal 🐶🐱",
    "localizacao": "Fortaleza e Eusébio, CE ",
    "descricao": "A ONG ABRACE, localizada em Fortaleza-CE, atua há mais de 13 anos no resgate, cuidado e adoção de cães e gatos em situação de abandono. Fundada e presidida por Cristiane, a iniciativa oferece acolhimento, tratamento veterinário e busca por famílias que possam proporcionar amor e um lar definitivo.",
    "tags": ["Instagram", "Facebook", "WhatsApp"],
    "logo": "/ongslogos/ongabracelogo.png",
    "links": {
      "instagram": "https://www.instagram.com/ong.abrace",
      "facebook": "https://facebook.com/caosemdono",
      "whatsapp": "https://wa.me/5585977777777"
    },
    "contatos": {
      "email": "adocao@caosemdono.org",
      "telefone": "(85) 97777-7777"
    },
    "doacoes": {
      "pix": "caosemdono.pix@gmail.com",
      "banco": "Bradesco - Ag: 3456 C/C: 7890-1"
    }
  },
  {
    "id": 4,
    "nome": "Dory Cats",
    "subtitulo": "Alimentação e Cuidados",
    "localizacao": "Fortaleza, CE - ",
    "descricao": "Gatos resgatados para adoção. Não recebemos animais",
    "tags": ["Instagram", "WhatsApp", "Site"],
    "logo": "/ongslogos/dorycatslogo.jpg",
    "links": {
      "instagram": "https://www.instagram.com/dorycats",
      "whatsapp": "https://wa.me/5585966666666",
      "site": "https://patinhascarentes.org"
    },
    "contatos": {
      "email": "dorycats10@gmail.com",
      "telefone": "(85) 96666-6666"
    },
    "doacoes": {
      "pix": "patinhas@pix.com",
      "banco": "Itaú - Ag: 8901 C/C: 23456-7"
    }
  },
  {
    "id": 5,
    "nome": "Rede de Resgate",
    "subtitulo": "❤️ Atuamos com amor pela causa animal",
    "localizacao": "Fortaleza, CE - ",
    "descricao": "🔗 Conectamos quem pode ajudar a quem precisa 🚫 Sem abrigo",
    "tags": ["Instagram", "WhatsApp", "Site"],
    "logo": "/ongslogos/redederesgatelogo.jpg",
    "links": {
      "instagram": "https://www.instagram.com/redederesgate_24",
      "whatsapp": "https://wa.me/5585966666666",
      "site": "https://rifa.digital/s/gZ7Xy8qBK9g?fbclid=PAZXh0bgNhZW0CMTEAAafLZUxc88iqk5QuqMdt3Vf3B_AA-ZqNVmfQN_eaUmtrTVjIiXa1qkhpi-mGRA_aem_yfMPmf4LLFoho81hUOZguA"
    },
    "contatos": {
      "email": "rederesgate24@outlook.com",
      "telefone": "(85) 96666-6666"
    },
    "doacoes": {
      "pix": "patinhas@pix.com",
      "banco": "Itaú - Ag: 8901 C/C: 23456-7"
    }
  },
  {
    "id": 6,
    "nome": "Causa Pet",
    "subtitulo": "Instituto Causa Pet® | Lar Temporário",
    "localizacao": "Fortaleza, CE ",
    "descricao": "⛑1.485 Resgates 🐶🐱1.241 Adoções 📈1.816 Castrações",
    "tags": ["Instagram", "WhatsApp", "Site"],
    "logo": "/ongslogos/causapetlogo.webp",
    "links": {
      "instagram": "https://www.instagram.com/causapet",
      "whatsapp": "https://wa.me/5585966666666",
      "site": "https://rifa.digital/s/K59lxIAuiDZ"
    },
    "contatos": {
      "email": "queroajudar@causapet.com",
      "telefone": "(85) 96666-6666"
    },
    "doacoes": {
      "pix": "patinhas@pix.com",
      "banco": "Itaú - Ag: 8901 C/C: 23456-7"
    }
  }
]